cycden/__init__.py
cycden/cycden.py
cycden/base/__init__.py
cycden/base/graph_matrices.py
cycden/base/graph_partition.py
cycden/base/graph_properties.py
cycden/base/graph_topindices.py
cycden/reg/__init__.py
cycden/reg/graph_matrices_db.py
cycden/reg/graph_partition_db.py
cycden/reg/graph_property_db.py
cycden/reg/topo_formulas_db.py
cycden-0.1.0.dist-info/METADATA
cycden-0.1.0.dist-info/WHEEL
cycden-0.1.0.dist-info/top_level.txt
cycden-0.1.0.dist-info/RECORD
