Metadata-Version: 2.4
Name: cycden
Version: 0.1.0
Summary: A generator and analytical toolkit for cyclic dendrimer graphs CD(m, n).
Author-email: Daniel Cabugao <danielcabugao8@gmail.com>
License: MIT
Project-URL: Homepage, https://github.com/fresnel-uv/cycden
Project-URL: Repository, https://github.com/fresnel-uv/cycden
Requires-Python: >=3.8
Requires-Dist: networkx>=3.1
Requires-Dist: pandas>=1.5
Requires-Dist: numpy>=1.21
